MANIFEST.in
README.rst
setup.cfg
setup.py
rasblite/__init__.py
rasblite/engine.py
rasblite/run.py
rasblite.egg-info/PKG-INFO
rasblite.egg-info/SOURCES.txt
rasblite.egg-info/dependency_links.txt
rasblite.egg-info/entry_points.txt
rasblite.egg-info/top_level.txt
rasblite/resources/favicon.ico