Metadata-Version: 1.1
Name: rasblite
Version: 1.0.0
Summary: Lightweight RESTful API Server Builder
Home-page: https://github.com/timrainbow/rasblite
Author: Tim Rainbow
Author-email: tim@timrainbow.com
License: MIT License
Download-URL: https://github.com/timrainbow/rasblite/archive/1.0.0.tar.gz
Keywords: REST,RESTFul,testing,Lightweight,HTTP,server,builder
Platform: UNKNOWN
Classifier: Programming Language :: Python :: 3 :: Only
Classifier: Development Status :: 5 - Production/Stable
Classifier: Natural Language :: English
Classifier: Environment :: Web Environment
Classifier: Intended Audience :: Developers
Classifier: License :: OSI Approved :: MIT License
Classifier: Operating System :: Unix
Classifier: Topic :: Software Development :: Libraries :: Python Modules
Classifier: Topic :: Software Development :: Libraries :: Application Frameworks
Classifier: Topic :: Internet :: WWW/HTTP :: Dynamic Content
